{
    "uid": "d3ae4c61-94dc-4948-b892-291598a32c81",
    "name": "model_2",
    "preprocessing": [
        {
            "missing_values": [
                {
                    "fill_method": "na_fill_median",
                    "fill_params": {
                        "workclass": "Private",
                        "occupation": "Prof-specialty",
                        "native-country": "United-States"
                    }
                }
            ],
            "categorical": [
                {
                    "convert_method": "categorical_to_int",
                    "convert_params": {
                        "workclass": {
                            "Federal-gov": 0,
                            "Local-gov": 1,
                            "Never-worked": 2,
                            "Private": 3,
                            "Self-emp-inc": 4,
                            "Self-emp-not-inc": 5,
                            "State-gov": 6,
                            "Without-pay": 7
                        },
                        "education": {
                            "10th": 0,
                            "11th": 1,
                            "12th": 2,
                            "1st-4th": 3,
                            "5th-6th": 4,
                            "7th-8th": 5,
                            "9th": 6,
                            "Assoc-acdm": 7,
                            "Assoc-voc": 8,
                            "Bachelors": 9,
                            "Doctorate": 10,
                            "HS-grad": 11,
                            "Masters": 12,
                            "Preschool": 13,
                            "Prof-school": 14,
                            "Some-college": 15
                        },
                        "marital-status": {
                            "Divorced": 0,
                            "Married-AF-spouse": 1,
                            "Married-civ-spouse": 2,
                            "Married-spouse-absent": 3,
                            "Never-married": 4,
                            "Separated": 5,
                            "Widowed": 6
                        },
                        "occupation": {
                            "Adm-clerical": 0,
                            "Armed-Forces": 1,
                            "Craft-repair": 2,
                            "Exec-managerial": 3,
                            "Farming-fishing": 4,
                            "Handlers-cleaners": 5,
                            "Machine-op-inspct": 6,
                            "Other-service": 7,
                            "Priv-house-serv": 8,
                            "Prof-specialty": 9,
                            "Protective-serv": 10,
                            "Sales": 11,
                            "Tech-support": 12,
                            "Transport-moving": 13
                        },
                        "relationship": {
                            "Husband": 0,
                            "Not-in-family": 1,
                            "Other-relative": 2,
                            "Own-child": 3,
                            "Unmarried": 4,
                            "Wife": 5
                        },
                        "race": {
                            "Amer-Indian-Eskimo": 0,
                            "Asian-Pac-Islander": 1,
                            "Black": 2,
                            "Other": 3,
                            "White": 4
                        },
                        "sex": {
                            "Female": 0,
                            "Male": 1
                        },
                        "native-country": {
                            "Cambodia": 0,
                            "Canada": 1,
                            "China": 2,
                            "Columbia": 3,
                            "Cuba": 4,
                            "Dominican-Republic": 5,
                            "Ecuador": 6,
                            "El-Salvador": 7,
                            "England": 8,
                            "France": 9,
                            "Germany": 10,
                            "Greece": 11,
                            "Guatemala": 12,
                            "Haiti": 13,
                            "Holand-Netherlands": 14,
                            "Honduras": 15,
                            "Hong": 16,
                            "Hungary": 17,
                            "India": 18,
                            "Iran": 19,
                            "Ireland": 20,
                            "Italy": 21,
                            "Jamaica": 22,
                            "Japan": 23,
                            "Laos": 24,
                            "Mexico": 25,
                            "Nicaragua": 26,
                            "Outlying-US(Guam-USVI-etc)": 27,
                            "Peru": 28,
                            "Philippines": 29,
                            "Poland": 30,
                            "Portugal": 31,
                            "Puerto-Rico": 32,
                            "Scotland": 33,
                            "South": 34,
                            "Taiwan": 35,
                            "Thailand": 36,
                            "Trinadad&Tobago": 37,
                            "United-States": 38,
                            "Vietnam": 39,
                            "Yugoslavia": 40
                        }
                    }
                }
            ],
            "scale": [
                {
                    "scale": [
                        13.665128481373122,
                        1.1133987186818366,
                        105705.69316331249,
                        3.8701063236145656,
                        2.5715726631949947,
                        1.5065501518590596,
                        3.9679052483531616,
                        1.6073806169346085,
                        0.8459689194491691,
                        0.46969778109745935,
                        7580.785181219326,
                        400.14647571562176,
                        12.450445898849468,
                        6.106490215615385
                    ],
                    "mean": [
                        38.6231884057971,
                        3.099193780593147,
                        190021.07308762838,
                        10.301180535560034,
                        10.088876091755447,
                        2.6111910931951243,
                        6.14041654669354,
                        1.44332469526826,
                        3.6671945484211537,
                        0.6714176024570496,
                        1102.0161723773874,
                        85.83722046261637,
                        40.445436222286204,
                        36.39164027257894
                    ],
                    "var": [
                        186.7357364124349,
                        1.2396567067623556,
                        11173693567.13637,
                        14.97772295608145,
                        6.612985962091798,
                        2.269693360066556,
                        15.744272059908566,
                        2.583672447697083,
                        0.7156634126739947,
                        0.22061600556787686,
                        57468303.96379452,
                        160117.20202763268,
                        155.01360308017755,
                        37.289222753406435
                    ],
                    "n_samples_seen": 20838,
                    "columns": [
                        "age",
                        "workclass",
                        "fnlwgt",
                        "education",
                        "education-num",
                        "marital-status",
                        "occupation",
                        "relationship",
                        "race",
                        "sex",
                        "capital-gain",
                        "capital-loss",
                        "hours-per-week",
                        "native-country"
                    ],
                    "scale_method": "scale_normal"
                }
            ],
            "categorical_y": {
                "<=50K": 0,
                ">50K": 1
            },
            "ml_task": "binary_classification"
        },
        {
            "missing_values": [
                {
                    "fill_method": "na_fill_median",
                    "fill_params": {
                        "workclass": "Private",
                        "occupation": "Prof-specialty",
                        "native-country": "United-States"
                    }
                }
            ],
            "categorical": [
                {
                    "convert_method": "categorical_to_int",
                    "convert_params": {
                        "workclass": {
                            "Federal-gov": 0,
                            "Local-gov": 1,
                            "Never-worked": 2,
                            "Private": 3,
                            "Self-emp-inc": 4,
                            "Self-emp-not-inc": 5,
                            "State-gov": 6,
                            "Without-pay": 7
                        },
                        "education": {
                            "10th": 0,
                            "11th": 1,
                            "12th": 2,
                            "1st-4th": 3,
                            "5th-6th": 4,
                            "7th-8th": 5,
                            "9th": 6,
                            "Assoc-acdm": 7,
                            "Assoc-voc": 8,
                            "Bachelors": 9,
                            "Doctorate": 10,
                            "HS-grad": 11,
                            "Masters": 12,
                            "Preschool": 13,
                            "Prof-school": 14,
                            "Some-college": 15
                        },
                        "marital-status": {
                            "Divorced": 0,
                            "Married-AF-spouse": 1,
                            "Married-civ-spouse": 2,
                            "Married-spouse-absent": 3,
                            "Never-married": 4,
                            "Separated": 5,
                            "Widowed": 6
                        },
                        "occupation": {
                            "Adm-clerical": 0,
                            "Armed-Forces": 1,
                            "Craft-repair": 2,
                            "Exec-managerial": 3,
                            "Farming-fishing": 4,
                            "Handlers-cleaners": 5,
                            "Machine-op-inspct": 6,
                            "Other-service": 7,
                            "Priv-house-serv": 8,
                            "Prof-specialty": 9,
                            "Protective-serv": 10,
                            "Sales": 11,
                            "Tech-support": 12,
                            "Transport-moving": 13
                        },
                        "relationship": {
                            "Husband": 0,
                            "Not-in-family": 1,
                            "Other-relative": 2,
                            "Own-child": 3,
                            "Unmarried": 4,
                            "Wife": 5
                        },
                        "race": {
                            "Amer-Indian-Eskimo": 0,
                            "Asian-Pac-Islander": 1,
                            "Black": 2,
                            "Other": 3,
                            "White": 4
                        },
                        "sex": {
                            "Female": 0,
                            "Male": 1
                        },
                        "native-country": {
                            "Cambodia": 0,
                            "Canada": 1,
                            "China": 2,
                            "Columbia": 3,
                            "Cuba": 4,
                            "Dominican-Republic": 5,
                            "Ecuador": 6,
                            "El-Salvador": 7,
                            "England": 8,
                            "France": 9,
                            "Germany": 10,
                            "Greece": 11,
                            "Guatemala": 12,
                            "Haiti": 13,
                            "Holand-Netherlands": 14,
                            "Honduras": 15,
                            "Hong": 16,
                            "Hungary": 17,
                            "India": 18,
                            "Iran": 19,
                            "Ireland": 20,
                            "Italy": 21,
                            "Jamaica": 22,
                            "Japan": 23,
                            "Laos": 24,
                            "Mexico": 25,
                            "Nicaragua": 26,
                            "Outlying-US(Guam-USVI-etc)": 27,
                            "Peru": 28,
                            "Philippines": 29,
                            "Poland": 30,
                            "Portugal": 31,
                            "Puerto-Rico": 32,
                            "Scotland": 33,
                            "South": 34,
                            "Taiwan": 35,
                            "Thailand": 36,
                            "Trinadad&Tobago": 37,
                            "United-States": 38,
                            "Vietnam": 39,
                            "Yugoslavia": 40
                        }
                    }
                }
            ],
            "scale": [
                {
                    "scale": [
                        13.710693682447914,
                        1.1093441544985874,
                        107360.25676139104,
                        3.859486528434405,
                        2.5771449351846067,
                        1.5040475021912414,
                        3.9728596876624698,
                        1.6064828002515406,
                        0.844100805589671,
                        0.47013389191294425,
                        7430.802035611663,
                        403.90353498861543,
                        12.290372839833157,
                        6.01064258984617
                    ],
                    "mean": [
                        38.612390824455325,
                        3.0864766292350514,
                        191127.3767156157,
                        10.31826470870525,
                        10.092619253287264,
                        2.6217007390344564,
                        6.171801516460313,
                        1.445868125539879,
                        3.6691621076878778,
                        0.6702178711968519,
                        1086.210816777042,
                        87.6062002111527,
                        40.464967847202225,
                        36.44126115750072
                    ],
                    "var": [
                        187.98312125391715,
                        1.2306444531201859,
                        11526224731.87181,
                        14.895636263166654,
                        6.641676016947671,
                        2.262158888847712,
                        15.783614097853539,
                        2.580786987504031,
                        0.7125061699971316,
                        0.22102587632521192,
                        55216818.89245043,
                        163138.06557629968,
                        151.05326454210854,
                        36.12782434287267
                    ],
                    "n_samples_seen": 20838,
                    "columns": [
                        "age",
                        "workclass",
                        "fnlwgt",
                        "education",
                        "education-num",
                        "marital-status",
                        "occupation",
                        "relationship",
                        "race",
                        "sex",
                        "capital-gain",
                        "capital-loss",
                        "hours-per-week",
                        "native-country"
                    ],
                    "scale_method": "scale_normal"
                }
            ],
            "categorical_y": {
                "<=50K": 0,
                ">50K": 1
            },
            "ml_task": "binary_classification"
        },
        {
            "missing_values": [
                {
                    "fill_method": "na_fill_median",
                    "fill_params": {
                        "workclass": "Private",
                        "occupation": "Prof-specialty",
                        "native-country": "United-States"
                    }
                }
            ],
            "categorical": [
                {
                    "convert_method": "categorical_to_int",
                    "convert_params": {
                        "workclass": {
                            "Federal-gov": 0,
                            "Local-gov": 1,
                            "Never-worked": 2,
                            "Private": 3,
                            "Self-emp-inc": 4,
                            "Self-emp-not-inc": 5,
                            "State-gov": 6,
                            "Without-pay": 7
                        },
                        "education": {
                            "10th": 0,
                            "11th": 1,
                            "12th": 2,
                            "1st-4th": 3,
                            "5th-6th": 4,
                            "7th-8th": 5,
                            "9th": 6,
                            "Assoc-acdm": 7,
                            "Assoc-voc": 8,
                            "Bachelors": 9,
                            "Doctorate": 10,
                            "HS-grad": 11,
                            "Masters": 12,
                            "Preschool": 13,
                            "Prof-school": 14,
                            "Some-college": 15
                        },
                        "marital-status": {
                            "Divorced": 0,
                            "Married-AF-spouse": 1,
                            "Married-civ-spouse": 2,
                            "Married-spouse-absent": 3,
                            "Never-married": 4,
                            "Separated": 5,
                            "Widowed": 6
                        },
                        "occupation": {
                            "Adm-clerical": 0,
                            "Armed-Forces": 1,
                            "Craft-repair": 2,
                            "Exec-managerial": 3,
                            "Farming-fishing": 4,
                            "Handlers-cleaners": 5,
                            "Machine-op-inspct": 6,
                            "Other-service": 7,
                            "Priv-house-serv": 8,
                            "Prof-specialty": 9,
                            "Protective-serv": 10,
                            "Sales": 11,
                            "Tech-support": 12,
                            "Transport-moving": 13
                        },
                        "relationship": {
                            "Husband": 0,
                            "Not-in-family": 1,
                            "Other-relative": 2,
                            "Own-child": 3,
                            "Unmarried": 4,
                            "Wife": 5
                        },
                        "race": {
                            "Amer-Indian-Eskimo": 0,
                            "Asian-Pac-Islander": 1,
                            "Black": 2,
                            "Other": 3,
                            "White": 4
                        },
                        "sex": {
                            "Female": 0,
                            "Male": 1
                        },
                        "native-country": {
                            "Cambodia": 0,
                            "Canada": 1,
                            "China": 2,
                            "Columbia": 3,
                            "Cuba": 4,
                            "Dominican-Republic": 5,
                            "Ecuador": 6,
                            "El-Salvador": 7,
                            "England": 8,
                            "France": 9,
                            "Germany": 10,
                            "Greece": 11,
                            "Guatemala": 12,
                            "Haiti": 13,
                            "Holand-Netherlands": 14,
                            "Honduras": 15,
                            "Hong": 16,
                            "Hungary": 17,
                            "India": 18,
                            "Iran": 19,
                            "Ireland": 20,
                            "Italy": 21,
                            "Jamaica": 22,
                            "Japan": 23,
                            "Laos": 24,
                            "Mexico": 25,
                            "Nicaragua": 26,
                            "Outlying-US(Guam-USVI-etc)": 27,
                            "Peru": 28,
                            "Philippines": 29,
                            "Poland": 30,
                            "Portugal": 31,
                            "Puerto-Rico": 32,
                            "Scotland": 33,
                            "South": 34,
                            "Taiwan": 35,
                            "Thailand": 36,
                            "Trinadad&Tobago": 37,
                            "United-States": 38,
                            "Vietnam": 39,
                            "Yugoslavia": 40
                        }
                    }
                }
            ],
            "scale": [
                {
                    "scale": [
                        13.669766031948244,
                        1.1087393459792863,
                        106584.68026601135,
                        3.8479368806128913,
                        2.568888211151249,
                        1.4986991148283415,
                        3.9681330681457556,
                        1.6077894248096767,
                        0.8442629825468214,
                        0.46795464761126865,
                        7161.069446429547,
                        405.32326296668936,
                        12.387493681915583,
                        6.097339820524173
                    ],
                    "mean": [
                        38.63192244937134,
                        3.090795661771763,
                        190253.4252807371,
                        10.31140224589692,
                        10.090891640272579,
                        2.60715999616086,
                        6.167578462424417,
                        1.4414051252519435,
                        3.67117765620501,
                        0.6761205489970247,
                        1038.2897590939629,
                        87.99323351569248,
                        40.4854592571264,
                        36.39874268163931
                    ],
                    "var": [
                        186.86250336820606,
                        1.2293029373225752,
                        11360294067.407867,
                        14.806618237180867,
                        6.599186641391866,
                        2.246099036787254,
                        15.74608004651185,
                        2.5849868345298312,
                        0.7127799836988544,
                        0.2189815522209866,
                        51280915.61658677,
                        164286.94750196402,
                        153.44999971949846,
                        37.177552886949755
                    ],
                    "n_samples_seen": 20838,
                    "columns": [
                        "age",
                        "workclass",
                        "fnlwgt",
                        "education",
                        "education-num",
                        "marital-status",
                        "occupation",
                        "relationship",
                        "race",
                        "sex",
                        "capital-gain",
                        "capital-loss",
                        "hours-per-week",
                        "native-country"
                    ],
                    "scale_method": "scale_normal"
                }
            ],
            "categorical_y": {
                "<=50K": 0,
                ">50K": 1
            },
            "ml_task": "binary_classification"
        },
        {
            "missing_values": [
                {
                    "fill_method": "na_fill_median",
                    "fill_params": {
                        "workclass": "Private",
                        "occupation": "Prof-specialty",
                        "native-country": "United-States"
                    }
                }
            ],
            "categorical": [
                {
                    "convert_method": "categorical_to_int",
                    "convert_params": {
                        "workclass": {
                            "Federal-gov": 0,
                            "Local-gov": 1,
                            "Never-worked": 2,
                            "Private": 3,
                            "Self-emp-inc": 4,
                            "Self-emp-not-inc": 5,
                            "State-gov": 6,
                            "Without-pay": 7
                        },
                        "education": {
                            "10th": 0,
                            "11th": 1,
                            "12th": 2,
                            "1st-4th": 3,
                            "5th-6th": 4,
                            "7th-8th": 5,
                            "9th": 6,
                            "Assoc-acdm": 7,
                            "Assoc-voc": 8,
                            "Bachelors": 9,
                            "Doctorate": 10,
                            "HS-grad": 11,
                            "Masters": 12,
                            "Preschool": 13,
                            "Prof-school": 14,
                            "Some-college": 15
                        },
                        "marital-status": {
                            "Divorced": 0,
                            "Married-AF-spouse": 1,
                            "Married-civ-spouse": 2,
                            "Married-spouse-absent": 3,
                            "Never-married": 4,
                            "Separated": 5,
                            "Widowed": 6
                        },
                        "occupation": {
                            "Adm-clerical": 0,
                            "Armed-Forces": 1,
                            "Craft-repair": 2,
                            "Exec-managerial": 3,
                            "Farming-fishing": 4,
                            "Handlers-cleaners": 5,
                            "Machine-op-inspct": 6,
                            "Other-service": 7,
                            "Priv-house-serv": 8,
                            "Prof-specialty": 9,
                            "Protective-serv": 10,
                            "Sales": 11,
                            "Tech-support": 12,
                            "Transport-moving": 13
                        },
                        "relationship": {
                            "Husband": 0,
                            "Not-in-family": 1,
                            "Other-relative": 2,
                            "Own-child": 3,
                            "Unmarried": 4,
                            "Wife": 5
                        },
                        "race": {
                            "Amer-Indian-Eskimo": 0,
                            "Asian-Pac-Islander": 1,
                            "Black": 2,
                            "Other": 3,
                            "White": 4
                        },
                        "sex": {
                            "Female": 0,
                            "Male": 1
                        },
                        "native-country": {
                            "Cambodia": 0,
                            "Canada": 1,
                            "China": 2,
                            "Columbia": 3,
                            "Cuba": 4,
                            "Dominican-Republic": 5,
                            "Ecuador": 6,
                            "El-Salvador": 7,
                            "England": 8,
                            "France": 9,
                            "Germany": 10,
                            "Greece": 11,
                            "Guatemala": 12,
                            "Haiti": 13,
                            "Honduras": 14,
                            "Hong": 15,
                            "Hungary": 16,
                            "India": 17,
                            "Iran": 18,
                            "Ireland": 19,
                            "Italy": 20,
                            "Jamaica": 21,
                            "Japan": 22,
                            "Laos": 23,
                            "Mexico": 24,
                            "Nicaragua": 25,
                            "Outlying-US(Guam-USVI-etc)": 26,
                            "Peru": 27,
                            "Philippines": 28,
                            "Poland": 29,
                            "Portugal": 30,
                            "Puerto-Rico": 31,
                            "Scotland": 32,
                            "South": 33,
                            "Taiwan": 34,
                            "Thailand": 35,
                            "Trinadad&Tobago": 36,
                            "United-States": 37,
                            "Vietnam": 38,
                            "Yugoslavia": 39
                        }
                    }
                }
            ],
            "scale": [
                {
                    "scale": [
                        13.671722933256722,
                        1.1125469874942995,
                        105889.56613884507,
                        3.8535715038849445,
                        2.573538467944618,
                        1.4994255401514371,
                        3.9622955278238328,
                        1.6041036057956137,
                        0.845864845054189,
                        0.46925241841057713,
                        7357.57161658559,
                        398.17161818218443,
                        12.403775357951831,
                        5.86429474218187
                    ],
                    "mean": [
                        38.61572052401747,
                        3.092758769614665,
                        190209.84807332404,
                        10.30999568117472,
                        10.100436681222707,
                        2.6081865732520755,
                        6.137530591679063,
                        1.437305053025577,
                        3.6685061663227603,
                        0.6726330438120831,
                        1068.162915686933,
                        85.94097605451317,
                        40.46355391333557,
                        35.46110657901051
                    ],
                    "var": [
                        186.9160079637378,
                        1.2377607993826407,
                        11212600217.072844,
                        14.850013335554072,
                        6.623100245990732,
                        2.248276950458429,
                        15.699785849812747,
                        2.57314837812649,
                        0.7154873360985472,
                        0.22019783218417535,
                        54133860.093185894,
                        158540.63752581924,
                        153.85364313053307,
                        34.38995282318192
                    ],
                    "n_samples_seen": 20839,
                    "columns": [
                        "age",
                        "workclass",
                        "fnlwgt",
                        "education",
                        "education-num",
                        "marital-status",
                        "occupation",
                        "relationship",
                        "race",
                        "sex",
                        "capital-gain",
                        "capital-loss",
                        "hours-per-week",
                        "native-country"
                    ],
                    "scale_method": "scale_normal"
                }
            ],
            "categorical_y": {
                "<=50K": 0,
                ">50K": 1
            },
            "ml_task": "binary_classification"
        },
        {
            "missing_values": [
                {
                    "fill_method": "na_fill_median",
                    "fill_params": {
                        "workclass": "Private",
                        "occupation": "Prof-specialty",
                        "native-country": "United-States"
                    }
                }
            ],
            "categorical": [
                {
                    "convert_method": "categorical_to_int",
                    "convert_params": {
                        "workclass": {
                            "Federal-gov": 0,
                            "Local-gov": 1,
                            "Never-worked": 2,
                            "Private": 3,
                            "Self-emp-inc": 4,
                            "Self-emp-not-inc": 5,
                            "State-gov": 6,
                            "Without-pay": 7
                        },
                        "education": {
                            "10th": 0,
                            "11th": 1,
                            "12th": 2,
                            "1st-4th": 3,
                            "5th-6th": 4,
                            "7th-8th": 5,
                            "9th": 6,
                            "Assoc-acdm": 7,
                            "Assoc-voc": 8,
                            "Bachelors": 9,
                            "Doctorate": 10,
                            "HS-grad": 11,
                            "Masters": 12,
                            "Preschool": 13,
                            "Prof-school": 14,
                            "Some-college": 15
                        },
                        "marital-status": {
                            "Divorced": 0,
                            "Married-AF-spouse": 1,
                            "Married-civ-spouse": 2,
                            "Married-spouse-absent": 3,
                            "Never-married": 4,
                            "Separated": 5,
                            "Widowed": 6
                        },
                        "occupation": {
                            "Adm-clerical": 0,
                            "Armed-Forces": 1,
                            "Craft-repair": 2,
                            "Exec-managerial": 3,
                            "Farming-fishing": 4,
                            "Handlers-cleaners": 5,
                            "Machine-op-inspct": 6,
                            "Other-service": 7,
                            "Priv-house-serv": 8,
                            "Prof-specialty": 9,
                            "Protective-serv": 10,
                            "Sales": 11,
                            "Tech-support": 12,
                            "Transport-moving": 13
                        },
                        "relationship": {
                            "Husband": 0,
                            "Not-in-family": 1,
                            "Other-relative": 2,
                            "Own-child": 3,
                            "Unmarried": 4,
                            "Wife": 5
                        },
                        "race": {
                            "Amer-Indian-Eskimo": 0,
                            "Asian-Pac-Islander": 1,
                            "Black": 2,
                            "Other": 3,
                            "White": 4
                        },
                        "sex": {
                            "Female": 0,
                            "Male": 1
                        },
                        "native-country": {
                            "Cambodia": 0,
                            "Canada": 1,
                            "China": 2,
                            "Columbia": 3,
                            "Cuba": 4,
                            "Dominican-Republic": 5,
                            "Ecuador": 6,
                            "El-Salvador": 7,
                            "England": 8,
                            "France": 9,
                            "Germany": 10,
                            "Greece": 11,
                            "Guatemala": 12,
                            "Haiti": 13,
                            "Holand-Netherlands": 14,
                            "Honduras": 15,
                            "Hong": 16,
                            "Hungary": 17,
                            "India": 18,
                            "Iran": 19,
                            "Ireland": 20,
                            "Italy": 21,
                            "Jamaica": 22,
                            "Japan": 23,
                            "Laos": 24,
                            "Mexico": 25,
                            "Nicaragua": 26,
                            "Outlying-US(Guam-USVI-etc)": 27,
                            "Peru": 28,
                            "Philippines": 29,
                            "Poland": 30,
                            "Portugal": 31,
                            "Puerto-Rico": 32,
                            "Scotland": 33,
                            "South": 34,
                            "Taiwan": 35,
                            "Thailand": 36,
                            "Trinadad&Tobago": 37,
                            "United-States": 38,
                            "Vietnam": 39,
                            "Yugoslavia": 40
                        }
                    }
                }
            ],
            "scale": [
                {
                    "scale": [
                        13.660675665152857,
                        1.1046434708295938,
                        105842.73346717033,
                        3.86743704630975,
                        2.5649775345873005,
                        1.5062715923873886,
                        3.964619507684283,
                        1.6033025810195036,
                        0.8391331596680734,
                        0.4698843532049622,
                        7476.546802853245,
                        402.2063657336379,
                        12.354530136567734,
                        6.010187598756199
                    ],
                    "mean": [
                        38.72181966505111,
                        3.094342338883824,
                        189311.758481693,
                        10.308604059695762,
                        10.092662795719564,
                        2.609770142521234,
                        6.131484236287729,
                        1.4330342146936033,
                        3.672777004654734,
                        0.6709055137002735,
                        1082.9667930322953,
                        86.88953404673929,
                        40.44671049474543,
                        36.45405249772062
                    ],
                    "var": [
                        186.61405962849946,
                        1.2202371976464514,
                        11202684227.802458,
                        14.957069307169084,
                        6.579109752937546,
                        2.2688541100332396,
                        15.718207840710765,
                        2.5705791663038022,
                        0.7041444596545244,
                        0.22079130538684566,
                        55898752.09525508,
                        161769.96063666086,
                        152.63441489536035,
                        36.122354972242796
                    ],
                    "n_samples_seen": 20839,
                    "columns": [
                        "age",
                        "workclass",
                        "fnlwgt",
                        "education",
                        "education-num",
                        "marital-status",
                        "occupation",
                        "relationship",
                        "race",
                        "sex",
                        "capital-gain",
                        "capital-loss",
                        "hours-per-week",
                        "native-country"
                    ],
                    "scale_method": "scale_normal"
                }
            ],
            "categorical_y": {
                "<=50K": 0,
                ">50K": 1
            },
            "ml_task": "binary_classification"
        }
    ],
    "learners": [
        {
            "library_version": "0.22.2",
            "algorithm_name": "Logistic Regression",
            "algorithm_short_name": "Linear",
            "uid": "aae8ca87-31ec-4b33-b47a-a886247beeab",
            "params": {
                "model_type": "Linear",
                "ml_task": "binary_classification",
                "seed": 2
            }
        },
        {
            "library_version": "0.22.2",
            "algorithm_name": "Logistic Regression",
            "algorithm_short_name": "Linear",
            "uid": "97786cf1-c617-4981-afb0-1b400021cd7d",
            "params": {
                "model_type": "Linear",
                "ml_task": "binary_classification",
                "seed": 2
            }
        },
        {
            "library_version": "0.22.2",
            "algorithm_name": "Logistic Regression",
            "algorithm_short_name": "Linear",
            "uid": "51d36b95-9b8e-4152-9175-d9e30bfa77d5",
            "params": {
                "model_type": "Linear",
                "ml_task": "binary_classification",
                "seed": 2
            }
        },
        {
            "library_version": "0.22.2",
            "algorithm_name": "Logistic Regression",
            "algorithm_short_name": "Linear",
            "uid": "9c767cdb-57d9-41df-85df-914881f82cda",
            "params": {
                "model_type": "Linear",
                "ml_task": "binary_classification",
                "seed": 2
            }
        },
        {
            "library_version": "0.22.2",
            "algorithm_name": "Logistic Regression",
            "algorithm_short_name": "Linear",
            "uid": "2aaec475-355a-42c5-8ca9-bf1ad0a3b4ae",
            "params": {
                "model_type": "Linear",
                "ml_task": "binary_classification",
                "seed": 2
            }
        }
    ],
    "params": {
        "additional": {
            "max_steps": 1,
            "max_rows_limit": null,
            "max_cols_limit": null
        },
        "preprocessing": {
            "columns_preprocessing": {
                "age": [
                    "scale_normal"
                ],
                "workclass": [
                    "na_fill_median",
                    "categorical_to_int",
                    "scale_normal"
                ],
                "fnlwgt": [
                    "scale_normal"
                ],
                "education": [
                    "categorical_to_int",
                    "scale_normal"
                ],
                "education-num": [
                    "scale_normal"
                ],
                "marital-status": [
                    "categorical_to_int",
                    "scale_normal"
                ],
                "occupation": [
                    "na_fill_median",
                    "categorical_to_int",
                    "scale_normal"
                ],
                "relationship": [
                    "categorical_to_int",
                    "scale_normal"
                ],
                "race": [
                    "categorical_to_int",
                    "scale_normal"
                ],
                "sex": [
                    "categorical_to_int",
                    "scale_normal"
                ],
                "capital-gain": [
                    "scale_normal"
                ],
                "capital-loss": [
                    "scale_normal"
                ],
                "hours-per-week": [
                    "scale_normal"
                ],
                "native-country": [
                    "na_fill_median",
                    "categorical_to_int",
                    "scale_normal"
                ]
            },
            "target_preprocessing": [
                "na_exclude",
                "categorical_to_int"
            ],
            "ml_task": "binary_classification"
        },
        "validation": {
            "validation_type": "kfold",
            "k_folds": 5,
            "shuffle": true,
            "stratify": true,
            "X_train_path": "AutoML_1/X_train.parquet",
            "y_train_path": "AutoML_1/y_train.parquet",
            "results_path": "AutoML_1"
        },
        "learner": {
            "model_type": "Linear",
            "ml_task": "binary_classification",
            "seed": 2
        },
        "ml_task": "binary_classification",
        "explain_level": 2,
        "name": "model_2"
    },
    "saved": [
        "AutoML_1/model_2/learner_1.linear",
        "AutoML_1/model_2/learner_2.linear",
        "AutoML_1/model_2/learner_3.linear",
        "AutoML_1/model_2/learner_4.linear",
        "AutoML_1/model_2/learner_5.linear"
    ],
    "threshold": 0.28416490162615
}