{
    "uid": "94231b0e-26c1-44bb-a15b-55842205f029",
    "name": "model_46",
    "preprocessing": [
        {
            "scale_y": {
                "scale": [
                    0.5958440782649306
                ],
                "mean": [
                    2.7303275865089667
                ],
                "var": [
                    0.3550301656033847
                ],
                "n_samples_seen": 323,
                "columns": [
                    "target"
                ],
                "scale_method": "scale_log_and_normal",
                "X_min_values": [
                    5.6
                ]
            },
            "ml_task": "regression"
        },
        {
            "scale_y": {
                "scale": [
                    0.5732733136096282
                ],
                "mean": [
                    2.7666547158724115
                ],
                "var": [
                    0.32864229209696305
                ],
                "n_samples_seen": 323,
                "columns": [
                    "target"
                ],
                "scale_method": "scale_log_and_normal",
                "X_min_values": [
                    5.0
                ]
            },
            "ml_task": "regression"
        },
        {
            "scale_y": {
                "scale": [
                    0.5837104984713019
                ],
                "mean": [
                    2.7624399306224077
                ],
                "var": [
                    0.34071794602561567
                ],
                "n_samples_seen": 323,
                "columns": [
                    "target"
                ],
                "scale_method": "scale_log_and_normal",
                "X_min_values": [
                    5.0
                ]
            },
            "ml_task": "regression"
        },
        {
            "scale_y": {
                "scale": [
                    0.5671579417396811
                ],
                "mean": [
                    2.7561922602248683
                ],
                "var": [
                    0.3216681308783915
                ],
                "n_samples_seen": 323,
                "columns": [
                    "target"
                ],
                "scale_method": "scale_log_and_normal",
                "X_min_values": [
                    5.0
                ]
            },
            "ml_task": "regression"
        },
        {
            "scale_y": {
                "scale": [
                    0.5920756285149357
                ],
                "mean": [
                    2.752511109994634
                ],
                "var": [
                    0.3505535498813561
                ],
                "n_samples_seen": 324,
                "columns": [
                    "target"
                ],
                "scale_method": "scale_log_and_normal",
                "X_min_values": [
                    5.0
                ]
            },
            "ml_task": "regression"
        }
    ],
    "learners": [
        {
            "library_version": "0.23",
            "algorithm_name": "CatBoost",
            "algorithm_short_name": "CatBoost",
            "uid": "b34cef04-0d2a-4b1f-88ac-70b4c8a34641",
            "params": {
                "model_type": "CatBoost",
                "ml_task": "regression",
                "seed": 2,
                "learning_rate": 0.05,
                "depth": 8,
                "rsm": 0.5,
                "l2_leaf_reg": 3,
                "loss_function": "MAE"
            }
        },
        {
            "library_version": "0.23",
            "algorithm_name": "CatBoost",
            "algorithm_short_name": "CatBoost",
            "uid": "ebdd34c5-7c69-4de4-8ba7-f8329103073f",
            "params": {
                "model_type": "CatBoost",
                "ml_task": "regression",
                "seed": 2,
                "learning_rate": 0.05,
                "depth": 8,
                "rsm": 0.5,
                "l2_leaf_reg": 3,
                "loss_function": "MAE"
            }
        },
        {
            "library_version": "0.23",
            "algorithm_name": "CatBoost",
            "algorithm_short_name": "CatBoost",
            "uid": "e861c620-25ef-4df4-a057-151324094e1a",
            "params": {
                "model_type": "CatBoost",
                "ml_task": "regression",
                "seed": 2,
                "learning_rate": 0.05,
                "depth": 8,
                "rsm": 0.5,
                "l2_leaf_reg": 3,
                "loss_function": "MAE"
            }
        },
        {
            "library_version": "0.23",
            "algorithm_name": "CatBoost",
            "algorithm_short_name": "CatBoost",
            "uid": "f41496d1-cde7-46f4-bc13-696bc59e8cb3",
            "params": {
                "model_type": "CatBoost",
                "ml_task": "regression",
                "seed": 2,
                "learning_rate": 0.05,
                "depth": 8,
                "rsm": 0.5,
                "l2_leaf_reg": 3,
                "loss_function": "MAE"
            }
        },
        {
            "library_version": "0.23",
            "algorithm_name": "CatBoost",
            "algorithm_short_name": "CatBoost",
            "uid": "df4c8646-18f6-4739-bd3f-ff052a818892",
            "params": {
                "model_type": "CatBoost",
                "ml_task": "regression",
                "seed": 2,
                "learning_rate": 0.05,
                "depth": 8,
                "rsm": 0.5,
                "l2_leaf_reg": 3,
                "loss_function": "MAE"
            }
        }
    ],
    "params": {
        "additional": {
            "trees_in_step": 10,
            "train_cant_improve_limit": 5,
            "min_steps": 5,
            "max_steps": 500,
            "max_rows_limit": null,
            "max_cols_limit": null
        },
        "preprocessing": {
            "columns_preprocessing": {},
            "target_preprocessing": [
                "na_exclude",
                "scale_log_and_normal"
            ],
            "ml_task": "regression"
        },
        "validation": {
            "validation_type": "kfold",
            "k_folds": 5,
            "shuffle": true,
            "X_train_path": "AutoML_1/X_train.parquet",
            "y_train_path": "AutoML_1/y_train.parquet",
            "results_path": "AutoML_1"
        },
        "learner": {
            "model_type": "CatBoost",
            "ml_task": "regression",
            "seed": 2,
            "learning_rate": 0.05,
            "depth": 8,
            "rsm": 0.5,
            "l2_leaf_reg": 3,
            "loss_function": "MAE"
        },
        "ml_task": "regression",
        "explain_level": 2,
        "name": "model_46"
    },
    "saved": [
        "AutoML_1/model_46/learner_1.catboost",
        "AutoML_1/model_46/learner_2.catboost",
        "AutoML_1/model_46/learner_3.catboost",
        "AutoML_1/model_46/learner_4.catboost",
        "AutoML_1/model_46/learner_5.catboost"
    ]
}